odoo8_addon_stock_picking_package_preparation_line-8.0.1.0.1-py2.7-nspkg.pth
odoo8_addon_stock_picking_package_preparation_line-8.0.1.0.1.dist-info/METADATA
odoo8_addon_stock_picking_package_preparation_line-8.0.1.0.1.dist-info/RECORD
odoo8_addon_stock_picking_package_preparation_line-8.0.1.0.1.dist-info/WHEEL
odoo8_addon_stock_picking_package_preparation_line-8.0.1.0.1.dist-info/namespace_packages.txt
odoo8_addon_stock_picking_package_preparation_line-8.0.1.0.1.dist-info/top_level.txt
odoo_addons/stock_picking_package_preparation_line/README.rst
odoo_addons/stock_picking_package_preparation_line/__init__.py
odoo_addons/stock_picking_package_preparation_line/__openerp__.py
odoo_addons/stock_picking_package_preparation_line/i18n/am.po
odoo_addons/stock_picking_package_preparation_line/i18n/ar.po
odoo_addons/stock_picking_package_preparation_line/i18n/bg.po
odoo_addons/stock_picking_package_preparation_line/i18n/bs.po
odoo_addons/stock_picking_package_preparation_line/i18n/ca.po
odoo_addons/stock_picking_package_preparation_line/i18n/ca_ES.po
odoo_addons/stock_picking_package_preparation_line/i18n/cs.po
odoo_addons/stock_picking_package_preparation_line/i18n/da.po
odoo_addons/stock_picking_package_preparation_line/i18n/da_DK.po
odoo_addons/stock_picking_package_preparation_line/i18n/de.po
odoo_addons/stock_picking_package_preparation_line/i18n/el_GR.po
odoo_addons/stock_picking_package_preparation_line/i18n/en_GB.po
odoo_addons/stock_picking_package_preparation_line/i18n/es.po
odoo_addons/stock_picking_package_preparation_line/i18n/es_AR.po
odoo_addons/stock_picking_package_preparation_line/i18n/es_CL.po
odoo_addons/stock_picking_package_preparation_line/i18n/es_CO.po
odoo_addons/stock_picking_package_preparation_line/i18n/es_CR.po
odoo_addons/stock_picking_package_preparation_line/i18n/es_DO.po
odoo_addons/stock_picking_package_preparation_line/i18n/es_EC.po
odoo_addons/stock_picking_package_preparation_line/i18n/es_ES.po
odoo_addons/stock_picking_package_preparation_line/i18n/es_MX.po
odoo_addons/stock_picking_package_preparation_line/i18n/es_PE.po
odoo_addons/stock_picking_package_preparation_line/i18n/es_PY.po
odoo_addons/stock_picking_package_preparation_line/i18n/es_VE.po
odoo_addons/stock_picking_package_preparation_line/i18n/et.po
odoo_addons/stock_picking_package_preparation_line/i18n/eu.po
